brain_games/.flake8
brain_games/__init__.py
brain_games/cli.py
brain_games/pyproject.toml
brain_games/README.md
brain_games/scripts/__init__.py
brain_games/scripts/brain_even.py
brain_games/scripts/brain_games.py
brain_games/tests/__init__.py
lysenkov_code-0.1.0.dist-info/entry_points.txt
lysenkov_code-0.1.0.dist-info/METADATA
lysenkov_code-0.1.0.dist-info/WHEEL
lysenkov_code-0.1.0.dist-info/RECORD
