Metadata-Version: 2.1
Name: lysenkov-code
Version: 0.1.0
Summary: 
Author: Lysenkov Ilya
Author-email: lysenkov_iv21@mail.ru
Requires-Python: >=3.8.1,<4.0
Classifier: Programming Language :: Python :: 3
Classifier: Programming Language :: Python :: 3.9
Classifier: Programming Language :: Python :: 3.10
Classifier: Programming Language :: Python :: 3.11
Classifier: Programming Language :: Python :: 3.12
Requires-Dist: prompt (>=0.4.1,<0.5.0)
